[
  {
    "type": "constructor",
    "inputs": [
      {
        "name": "_agentPool",
        "type": "address",
        "internalType": "address"
      },
      {
        "name": "_entropy",
        "type": "address",
        "internalType": "address"
      }
    ],
    "stateMutability": "nonpayable"
  },
  {
    "type": "receive",
    "stateMutability": "payable"
  },
  {
    "type": "function",
    "name": "_processResult",
    "inputs": [
      {
        "name": "sequenceNumber",
        "type": "uint64",
        "internalType": "uint64"
      },
      {
        "name": "randomNumber",
        "type": "bytes32",
        "internalType": "bytes32"
      }
    ],
    "outputs": [],
    "stateMutability": "nonpayable"
  },
  {
    "type": "function",
    "name": "agentPool",
    "inputs": [],
    "outputs": [
      {
        "name": "",
        "type": "address",
        "internalType": "contract IAgentPool"
      }
    ],
    "stateMutability": "view"
  },
  {
    "type": "function",
    "name": "bets",
    "inputs": [
      {
        "name": "",
        "type": "uint64",
        "internalType": "uint64"
      }
    ],
    "outputs": [
      {
        "name": "agentId",
        "type": "uint256",
        "internalType": "uint256"
      },
      {
        "name": "side",
        "type": "bool",
        "internalType": "bool"
      },
      {
        "name": "amount",
        "type": "uint256",
        "internalType": "uint256"
      },
      {
        "name": "resolved",
        "type": "bool",
        "internalType": "bool"
      }
    ],
    "stateMutability": "view"
  },
  {
    "type": "function",
    "name": "entropy",
    "inputs": [],
    "outputs": [
      {
        "name": "",
        "type": "address",
        "internalType": "contract IEntropyV2"
      }
    ],
    "stateMutability": "view"
  },
  {
    "type": "function",
    "name": "getBet",
    "inputs": [
      {
        "name": "sequenceNumber",
        "type": "uint64",
        "internalType": "uint64"
      }
    ],
    "outputs": [
      {
        "name": "agentId",
        "type": "uint256",
        "internalType": "uint256"
      },
      {
        "name": "side",
        "type": "bool",
        "internalType": "bool"
      },
      {
        "name": "amount",
        "type": "uint256",
        "internalType": "uint256"
      },
      {
        "name": "resolved",
        "type": "bool",
        "internalType": "bool"
      }
    ],
    "stateMutability": "view"
  },
  {
    "type": "function",
    "name": "placeBet",
    "inputs": [
      {
        "name": "agentId",
        "type": "uint256",
        "internalType": "uint256"
      },
      {
        "name": "side",
        "type": "bool",
        "internalType": "bool"
      },
      {
        "name": "amount",
        "type": "uint256",
        "internalType": "uint256"
      }
    ],
    "outputs": [
      {
        "name": "sequenceNumber",
        "type": "uint64",
        "internalType": "uint64"
      }
    ],
    "stateMutability": "nonpayable"
  },
  {
    "type": "event",
    "name": "BetPlaced",
    "inputs": [
      {
        "name": "sequenceNumber",
        "type": "uint64",
        "indexed": true,
        "internalType": "uint64"
      },
      {
        "name": "agentId",
        "type": "uint256",
        "indexed": true,
        "internalType": "uint256"
      },
      {
        "name": "side",
        "type": "bool",
        "indexed": false,
        "internalType": "bool"
      },
      {
        "name": "amount",
        "type": "uint256",
        "indexed": false,
        "internalType": "uint256"
      }
    ],
    "anonymous": false
  },
  {
    "type": "event",
    "name": "BetResolved",
    "inputs": [
      {
        "name": "sequenceNumber",
        "type": "uint64",
        "indexed": true,
        "internalType": "uint64"
      },
      {
        "name": "agentId",
        "type": "uint256",
        "indexed": true,
        "internalType": "uint256"
      },
      {
        "name": "won",
        "type": "bool",
        "indexed": false,
        "internalType": "bool"
      },
      {
        "name": "payout",
        "type": "uint256",
        "indexed": false,
        "internalType": "uint256"
      }
    ],
    "anonymous": false
  },
  {
    "type": "error",
    "name": "ReentrancyGuardReentrantCall",
    "inputs": []
  }
]
